langchain_oci/__init__.py
langchain_oci/chat_models/__init__.py
langchain_oci/chat_models/oci_data_science.py
langchain_oci/chat_models/oci_generative_ai.py
langchain_oci/chat_models/providers/__init__.py
langchain_oci/chat_models/providers/base.py
langchain_oci/chat_models/providers/cohere.py
langchain_oci/chat_models/providers/generic.py
langchain_oci/common/__init__.py
langchain_oci/common/auth.py
langchain_oci/common/utils.py
langchain_oci/embeddings/__init__.py
langchain_oci/embeddings/oci_data_science_model_deployment_endpoint.py
langchain_oci/embeddings/oci_generative_ai.py
langchain_oci/llms/__init__.py
langchain_oci/llms/oci_data_science_model_deployment_endpoint.py
langchain_oci/llms/oci_generative_ai.py
langchain_oci/llms/utils.py
langchain_oci-0.2.2.dist-info/METADATA
langchain_oci-0.2.2.dist-info/WHEEL
langchain_oci-0.2.2.dist-info/licenses/LICENSE
langchain_oci-0.2.2.dist-info/RECORD
