Metadata-Version: 2.4
Name: langchain-oci
Version: 0.2.2
Summary: An integration package connecting OCI and LangChain
License-Expression: UPL-1.0
License-File: LICENSE
Requires-Python: >=3.9,<4.0
Classifier: Programming Language :: Python :: 3
Classifier: Programming Language :: Python :: 3.9
Classifier: Programming Language :: Python :: 3.10
Classifier: Programming Language :: Python :: 3.11
Classifier: Programming Language :: Python :: 3.12
Classifier: Programming Language :: Python :: 3.13
Classifier: Programming Language :: Python :: 3.14
Requires-Dist: aiohttp (>=3.12.14)
Requires-Dist: langchain (>=0.3.20,<1.0.0) ; python_version < "3.10"
Requires-Dist: langchain (>=1.0.0,<2.0.0) ; python_version >= "3.10"
Requires-Dist: langchain-core (>=0.3.78,<1.0.0) ; python_version < "3.10"
Requires-Dist: langchain-core (>=1.1.0,<2.0.0) ; python_version >= "3.10"
Requires-Dist: langchain-openai (>=0.3.35,<1.0.0) ; python_version < "3.10"
Requires-Dist: langchain-openai (>=1.1.0,<2.0.0) ; python_version >= "3.10"
Requires-Dist: oci (>=2.161.0)
Requires-Dist: oci-openai (>=1.0.0)
Requires-Dist: openai (>=2.6.1)
Requires-Dist: pydantic (>=2,<3)
Project-URL: Repository, https://github.com/oracle/langchain-oracle
Project-URL: Source Code, https://github.com/oracle/langchain-oracle/tree/main/libs/oci
